gisty
tests
