Metadata-Version: 2.1
Name: gisty
Version: 0.1.1
Summary: A cli utility for querying GitHub gists
Home-page: https://github.com/firegrass/gisty
Author: Patrick McEvoy
Author-email: patrick.mcevoy@gmail.com
License: UNKNOWN
Platform: UNKNOWN
Classifier: Programming Language :: Python :: 3
Classifier: License :: OSI Approved :: MIT License
Classifier: Operating System :: OS Independent
Requires-Python: >=3.6
